csvuniondiff/__init__.py
csvuniondiff/src/__init__.py
csvuniondiff/src/command.py
csvuniondiff/src/csvuniondiff.py
tests/__init__.py
tests/test_command.py
tests/test_csvuniondiff.py
csvuniondiff-0.0.0.dev1.dist-info/LICENSE
csvuniondiff-0.0.0.dev1.dist-info/METADATA
csvuniondiff-0.0.0.dev1.dist-info/WHEEL
csvuniondiff-0.0.0.dev1.dist-info/entry_points.txt
csvuniondiff-0.0.0.dev1.dist-info/top_level.txt
csvuniondiff-0.0.0.dev1.dist-info/RECORD
