Metadata-Version: 2.1
Name: csvuniondiff
Version: 0.0.0.dev1
Summary: A package for comparing CSV-like files through union and difference operations.
Home-page: https://github.com/BrianWeiHaoMa/csvuniondiff
Author: Brian Wei Hao Ma
Author-email: brianmaytc@gmail.com
License: MIT
Keywords: csv,diff,union,compare,files,command-line,tool,data,analysis,pandas,dataframes,comparison,merge,difference,columns,rows,data processing,data integration,file comparison,open source,csv files,xlsx files,json files,xml files,html files,cli tool,data matching,data alignment,data cleaning,double-check,data validation,validation,confirm,error detection,sql
Classifier: Development Status :: 4 - Beta
Classifier: Intended Audience :: Developers
Classifier: Intended Audience :: Financial and Insurance Industry
Classifier: License :: OSI Approved :: MIT License
Classifier: Operating System :: OS Independent
Classifier: Topic :: Software Development :: Testing
Classifier: Topic :: Utilities
Classifier: Topic :: Office/Business :: Financial :: Spreadsheet
Classifier: Programming Language :: Python :: 3.12
Classifier: Programming Language :: Python :: 3.11
Classifier: Programming Language :: Python :: 3.10
Requires-Python: >=3.10
License-File: LICENSE
Requires-Dist: pandas <3.0.0,>=2.2.2
